<?xml version="1.0" encoding="utf-8" ?>
<dwsync>
<file name="desert-NoSky.png" server="ec2-3-134-93-96.us-east-2.compute.amazonaws.com//var/www/html/" local="133532997490928688" remote="133533106940000000" Dst="1" />
<file name="desert-rock.png" server="ec2-3-134-93-96.us-east-2.compute.amazonaws.com//var/www/html/" local="133532996768034437" remote="133533106940000000" Dst="1" />
<file name="desert.png" server="ec2-3-134-93-96.us-east-2.compute.amazonaws.com//var/www/html/" local="133532998158909274" remote="133533106950000000" Dst="1" />
<file name="grass.png" server="ec2-3-134-93-96.us-east-2.compute.amazonaws.com//var/www/html/" local="133532998717306854" remote="133533106950000000" Dst="1" />
<file name="water.png" server="ec2-3-134-93-96.us-east-2.compute.amazonaws.com//var/www/html/" local="133532999004125505" remote="133533106950000000" Dst="1" />
<file name="waterfall.png" server="ec2-3-134-93-96.us-east-2.compute.amazonaws.com//var/www/html/" local="133532999300481518" remote="133533106950000000" Dst="1" />
<file name="meteor-desert.png" server="ec2-3-134-93-96.us-east-2.compute.amazonaws.com//var/www/html/" local="133533099845600233" remote="133533130060000000" Dst="1" />
<file name="dino-leaving.png" server="ec2-3-134-93-96.us-east-2.compute.amazonaws.com//var/www/html/" local="133533134833709191" remote="133533157220000000" Dst="1" />
</dwsync>